simplebot_stickers/__init__.py
simplebot_stickers/_version.py
simplebot_stickers/signal.py
simplebot_stickers/telegram.py
simplebot_stickers/util.py
simplebot_stickers-2.2.0.dist-info/LICENSE
simplebot_stickers-2.2.0.dist-info/METADATA
simplebot_stickers-2.2.0.dist-info/WHEEL
simplebot_stickers-2.2.0.dist-info/entry_points.txt
simplebot_stickers-2.2.0.dist-info/top_level.txt
simplebot_stickers-2.2.0.dist-info/RECORD
