Metadata-Version: 2.1
Name: simplebot-stickers
Version: 2.2.0
Summary: Sticker packs for all your Delta Chat needs (SimpleBot plugin)
Home-page: https://github.com/adbenitez/simplebot_stickers
Author: adbenitez
Author-email: adbenitez@nauta.cu
License: MPL
Keywords: simplebot plugin deltachat stickers
Platform: UNKNOWN
Classifier: Development Status :: 4 - Beta
Classifier: Environment :: Plugins
Classifier: Programming Language :: Python :: 3
Classifier: License :: OSI Approved :: Mozilla Public License 2.0 (MPL 2.0)
Classifier: Operating System :: OS Independent
Classifier: Topic :: Utilities
License-File: LICENSE
Requires-Dist: simplebot (>=2.4.0)
Requires-Dist: signalstickers-client (>=3.1.0)
Requires-Dist: emoji (>=1.6.1)
Requires-Dist: cachelib (>=0.4.1)
Requires-Dist: requests (>=2.26.0)
Requires-Dist: lottie (>=0.6.10)
Requires-Dist: CairoSVG (>=2.5.2)
Requires-Dist: Pillow (>=8.4.0)
Provides-Extra: dev
Requires-Dist: simplebot (>=2.4.0) ; extra == 'dev'
Requires-Dist: signalstickers-client (>=3.1.0) ; extra == 'dev'
Requires-Dist: emoji (>=1.6.1) ; extra == 'dev'
Requires-Dist: cachelib (>=0.4.1) ; extra == 'dev'
Requires-Dist: requests (>=2.26.0) ; extra == 'dev'
Requires-Dist: lottie (>=0.6.10) ; extra == 'dev'
Requires-Dist: CairoSVG (>=2.5.2) ; extra == 'dev'
Requires-Dist: Pillow (>=8.4.0) ; extra == 'dev'
Requires-Dist: pytest (>=6.2.5) ; extra == 'dev'
Requires-Dist: black (>=21.11b1) ; extra == 'dev'
Requires-Dist: mypy (>=0.910) ; extra == 'dev'
Requires-Dist: isort (>=5.10.1) ; extra == 'dev'
Requires-Dist: pylint (>=2.12.2) ; extra == 'dev'
Requires-Dist: pylama (>=8.3.6) ; extra == 'dev'
Requires-Dist: types-emoji (>=1.2.6) ; extra == 'dev'
Requires-Dist: types-requests (>=2.26.1) ; extra == 'dev'
Provides-Extra: test
Requires-Dist: pytest (>=6.2.5) ; extra == 'test'
